apns2/__init__.py
apns2/client.py
apns2/credentials.py
apns2/errors.py
apns2/payload.py
mopyapns-0.8.0.dist-info/METADATA
mopyapns-0.8.0.dist-info/WHEEL
mopyapns-0.8.0.dist-info/entry_points.txt
mopyapns-0.8.0.dist-info/licenses/LICENSE
test/__init__.py
test/eckey.pem
test/test_client.py
test/test_credentials.py
test/test_payload.py
mopyapns-0.8.0.dist-info/RECORD
