Metadata-Version: 2.1
Name: mopyapns
Version: 0.8.0
Summary: Modern Python APNs client! Supports http/2 and time sensitive notifications
Author-Email: =?utf-8?q?Magnus_L=C3=B8nseth?= <magnus@pling.care>
License: MIT
Classifier: Development Status :: 4 - Beta
Classifier: License :: OSI Approved :: MIT License
Classifier: Programming Language :: Python :: 3.10
Classifier: Programming Language :: Python :: 3.11
Classifier: Programming Language :: Python :: 3.12
Classifier: Programming Language :: Python :: 3.13
Classifier: Programming Language :: Python :: 3.14
Classifier: Topic :: Software Development :: Libraries
Requires-Python: <4.0,>=3.10
Requires-Dist: cryptography>=45.0.4
Requires-Dist: httpx[http2]>=0.28.1
Requires-Dist: pyjwt>=2.10.1
